bumpversion/__init__.py
bumpversion/__main__.py
bumpversion/cli.py
bumpversion/exceptions.py
bumpversion/functions.py
bumpversion/utils.py
bumpversion/vcs.py
bumpversion/version_part.py
bumpversion2-1.4.4.dist-info/LICENSE.rst
bumpversion2-1.4.4.dist-info/METADATA
bumpversion2-1.4.4.dist-info/WHEEL
bumpversion2-1.4.4.dist-info/entry_points.txt
bumpversion2-1.4.4.dist-info/RECORD
