Metadata-Version: 2.3
Name: bumpversion2
Version: 1.4.4
Summary: Make it easy to bump version by command line.
License: MIT
Keywords: bumpversion
Author: Waket Zheng
Author-email: waketzheng@gmail.com
Requires-Python: >=3.9
Classifier: License :: OSI Approved :: MIT License
Classifier: Programming Language :: Python :: 3
Classifier: Programming Language :: Python :: 3.9
Classifier: Programming Language :: Python :: 3.10
Classifier: Programming Language :: Python :: 3.11
Classifier: Programming Language :: Python :: 3.12
Classifier: Programming Language :: Python :: 3.13
